{
  "$schema": "https://ui.shadcn.com/schema/registry-item.json",
  "name": "s-top-menu",
  "title": "STopMenu",
  "description": "Top navigation bar with logo, search, menu tabs, operations and avatar slots.",
  "registryDependencies": [
    "@vc/volcengine-theme"
  ],
  "files": [
    {
      "path": "registry/base-nova/s-top-menu/s-top-menu.tsx",
      "content": "\"use client\";\n\nimport React, { useState, useEffect } from \"react\";\nimport type { CSSProperties, ReactNode } from \"react\";\nimport { cn } from \"@/lib/utils\";\n\ninterface MenuOption {\n  key: string;\n  value: string;\n}\n\ninterface STopMenuProps {\n  style?: CSSProperties;\n  className?: string;\n  leftCorner?: ReactNode;\n  logo?: ReactNode;\n  search?: ReactNode;\n  menuOptions?: MenuOption[];\n  operations?: ReactNode[];\n  avatar?: ReactNode;\n  content?: ReactNode;\n  showLeftMenu?: boolean;\n  onLeftCornerClick?: (visible: boolean) => void;\n}\n\ninterface SSubTopMenuProps {\n  logo?: ReactNode;\n  menuOptions?: MenuOption[];\n  operations?: ReactNode[] | ReactNode;\n  style?: CSSProperties;\n}\n\nfunction HamburgerIcon() {\n  return (\n    <svg width=\"20\" height=\"20\" viewBox=\"0 0 20 20\" fill=\"none\" xmlns=\"http://www.w3.org/2000/svg\">\n      <path d=\"M3 5h14M3 10h14M3 15h14\" stroke=\"currentColor\" strokeWidth=\"1.5\" strokeLinecap=\"round\" />\n    </svg>\n  );\n}\n\nfunction SearchIcon() {\n  return (\n    <svg width=\"16\" height=\"16\" viewBox=\"0 0 16 16\" fill=\"none\" xmlns=\"http://www.w3.org/2000/svg\">\n      <circle cx=\"7\" cy=\"7\" r=\"4.5\" stroke=\"currentColor\" strokeWidth=\"1.5\" />\n      <path d=\"M10.5 10.5L14 14\" stroke=\"currentColor\" strokeWidth=\"1.5\" strokeLinecap=\"round\" />\n    </svg>\n  );\n}\n\nconst STopMenu: React.FC<STopMenuProps> = (props) => {\n  const {\n    style,\n    className,\n    leftCorner,\n    logo,\n    search,\n    menuOptions = [],\n    operations = [],\n    avatar,\n    content,\n    showLeftMenu,\n    onLeftCornerClick,\n  } = props;\n\n  const [menuVisible, setMenuVisible] = useState(!showLeftMenu);\n  const [selectedKey, setSelectedKey] = useState<string>(menuOptions[0]?.key ?? \"\");\n\n  useEffect(() => {\n    if (showLeftMenu !== undefined) setMenuVisible(!showLeftMenu);\n  }, [showLeftMenu]);\n\n  const handleToggle = () => {\n    const next = !menuVisible;\n    setMenuVisible(next);\n    onLeftCornerClick?.(next);\n  };\n\n  return (\n    <div\n      className={cn(className)}\n      style={{\n        display: \"flex\",\n        alignItems: \"center\",\n        height: 56,\n        backgroundColor: \"var(--color-bg-1, #fff)\",\n        borderBottom: \"1px solid var(--color-border-2, #e5e6eb)\",\n        padding: \"0 16px\",\n        gap: 16,\n        ...style,\n      }}\n    >\n      <div style={{ display: \"flex\", alignItems: \"center\", gap: 12, flexShrink: 0 }}>\n        {leftCorner ?? (\n          <div\n            onClick={handleToggle}\n            style={{\n              cursor: \"pointer\",\n              display: \"flex\",\n              alignItems: \"center\",\n              justifyContent: \"center\",\n              width: 32,\n              height: 32,\n              borderRadius: \"var(--border-radius-small, 4px)\",\n              color: \"var(--color-text-2, #4e5969)\",\n            }}\n          >\n            <HamburgerIcon />\n          </div>\n        )}\n        {logo ?? (\n          <div\n            style={{\n              width: 32,\n              height: 32,\n              borderRadius: \"var(--border-radius-small, 4px)\",\n              backgroundColor: \"var(--color-fill-3, #c9cdd4)\",\n              display: \"flex\",\n              alignItems: \"center\",\n              justifyContent: \"center\",\n              fontSize: 12,\n              color: \"#fff\",\n              fontWeight: 600,\n            }}\n          >\n            L\n          </div>\n        )}\n      </div>\n\n      <div style={{ flex: 1, display: \"flex\", alignItems: \"center\", justifyContent: \"center\", minWidth: 0 }}>\n        {content}\n      </div>\n\n      <div style={{ display: \"flex\", alignItems: \"center\", gap: 16, flexShrink: 0 }}>\n        {search ?? (\n          <div\n            style={{\n              display: \"flex\",\n              alignItems: \"center\",\n              gap: 6,\n              padding: \"0 10px\",\n              height: 32,\n              borderRadius: \"var(--border-radius-small, 4px)\",\n              border: \"1px solid var(--color-border-3)\",\n              backgroundColor: \"transparent\",\n              color: \"var(--color-text-3, #86909c)\",\n              fontSize: 14,\n            }}\n          >\n            <SearchIcon />\n            <input\n              type=\"text\"\n              placeholder=\"请输入关键词进行搜索\"\n              style={{\n                border: \"none\",\n                outline: \"none\",\n                background: \"transparent\",\n                color: \"var(--color-text-1, #1d2129)\",\n                fontSize: 14,\n                width: 160,\n              }}\n            />\n          </div>\n        )}\n\n        {menuOptions.length > 0 && (\n          <div style={{ display: \"flex\", alignItems: \"center\", gap: 4, height: 56 }}>\n            {menuOptions.map((opt) => {\n              const isActive = opt.key === selectedKey;\n              return (\n                <div\n                  key={opt.key}\n                  onClick={() => setSelectedKey(opt.key)}\n                  style={{\n                    position: \"relative\",\n                    padding: \"0 12px\",\n                    height: 56,\n                    display: \"flex\",\n                    alignItems: \"center\",\n                    cursor: \"pointer\",\n                    fontSize: 14,\n                    color: isActive ? \"rgb(var(--primary-6, 22 93 255))\" : \"var(--color-text-2, #4e5969)\",\n                    fontWeight: isActive ? 500 : 400,\n                    transition: \"color 0.2s\",\n                  }}\n                >\n                  {opt.value}\n                  {isActive && (\n                    <div\n                      style={{\n                        position: \"absolute\",\n                        bottom: 0,\n                        left: 12,\n                        right: 12,\n                        height: 2,\n                        backgroundColor: \"rgb(var(--primary-6, 22 93 255))\",\n                        borderRadius: 1,\n                      }}\n                    />\n                  )}\n                </div>\n              );\n            })}\n          </div>\n        )}\n\n        {operations.length > 0 && (\n          <div style={{ display: \"flex\", alignItems: \"center\", gap: 8 }}>\n            {operations.map((op, idx) => (\n              <div key={idx}>{op}</div>\n            ))}\n          </div>\n        )}\n\n        {avatar ?? (\n          <div\n            style={{\n              width: 32,\n              height: 32,\n              borderRadius: \"50%\",\n              backgroundColor: \"#aaa\",\n              flexShrink: 0,\n            }}\n          />\n        )}\n      </div>\n    </div>\n  );\n};\n\nexport const SSubTopMenu: React.FC<SSubTopMenuProps> = (props) => {\n  const { logo, menuOptions = [], operations, style } = props;\n  const [selectedKey, setSelectedKey] = useState<string>(menuOptions[0]?.key ?? \"\");\n\n  const opArray = Array.isArray(operations) ? operations : operations ? [operations] : [];\n\n  return (\n    <div\n      style={{\n        display: \"flex\",\n        alignItems: \"center\",\n        height: 48,\n        backgroundColor: \"var(--color-bg-1, #fff)\",\n        borderBottom: \"1px solid var(--color-border-2, #e5e6eb)\",\n        padding: \"0 16px\",\n        gap: 16,\n        ...style,\n      }}\n    >\n      <div style={{ display: \"flex\", alignItems: \"center\", gap: 12, flexShrink: 0 }}>\n        {logo}\n      </div>\n\n      {menuOptions.length > 0 && (\n        <div style={{ display: \"flex\", alignItems: \"center\", gap: 4, height: 48, flex: 1 }}>\n          {menuOptions.map((opt) => {\n            const isActive = opt.key === selectedKey;\n            return (\n              <div\n                key={opt.key}\n                onClick={() => setSelectedKey(opt.key)}\n                style={{\n                  position: \"relative\",\n                  padding: \"0 12px\",\n                  height: 48,\n                  display: \"flex\",\n                  alignItems: \"center\",\n                  cursor: \"pointer\",\n                  fontSize: 14,\n                  color: isActive ? \"rgb(var(--primary-6, 22 93 255))\" : \"var(--color-text-2, #4e5969)\",\n                  fontWeight: isActive ? 500 : 400,\n                  transition: \"color 0.2s\",\n                }}\n              >\n                {opt.value}\n                {isActive && (\n                  <div\n                    style={{\n                      position: \"absolute\",\n                      bottom: 0,\n                      left: 12,\n                      right: 12,\n                      height: 2,\n                      backgroundColor: \"rgb(var(--primary-6, 22 93 255))\",\n                      borderRadius: 1,\n                    }}\n                  />\n                )}\n              </div>\n            );\n          })}\n        </div>\n      )}\n\n      {opArray.length > 0 && (\n        <div style={{ display: \"flex\", alignItems: \"center\", gap: 8, flexShrink: 0 }}>\n          {opArray.map((op, idx) => (\n            <div key={idx}>{op}</div>\n          ))}\n        </div>\n      )}\n    </div>\n  );\n};\n\nexport type { MenuOption, STopMenuProps, SSubTopMenuProps };\nexport default STopMenu;\n",
      "type": "registry:component",
      "target": "$ui/s-top-menu.tsx"
    }
  ],
  "docs": "STopMenu provides a Volcengine-style top navigation bar. Also exports SSubTopMenu for secondary navigation.",
  "type": "registry:ui"
}